{
  "Form No": "L-28",
  "Title": "UNIT LINKED BUSINESS-3A",
  "Part": "PART - C",
  "Company": "Canara HSBC Life Insurance Company Limited",
  "Former_Name": "Canara HSBC Oriental Bank of Commerce Life Insurance Company Limited",
  "Registration No": "136",
  "Date of Registration": "May 8, 2008",
  "Date": "As at {QUARTER_END_DATE}",
  "Statement_Purpose": "Statement of NAV of Segregated Funds",
  "Currency": "₹ in Lacs",
  "PagesUsed": "3-6",
  "Headers": {
    "No": ["No"],
    "Fund_Name": ["Fund Name"],
    "SFIN": ["SFIN"],
    "Date_of_Launch": ["Date of Launch"],
    "Par_Non_Par": ["Par/Non Par"],
    "Assets_Under_Management": ["Assets Under Management on the above date", "(₹ in Lacs)"],
    "NAV_as_per_LB2": ["NAV as per LB 2"],
    "NAV_as_on_above_date": ["NAV as on the above date*"],
    "Previous_Qtr_NAV": ["Previous Qtr NAV"],
    "Second_Previous_Qtr_NAV": ["2nd Previous Qtr NAV"],
    "Third_Previous_Qtr_NAV": ["3rd Previous Qtr NAV"],
    "Fourth_Previous_Qtr_NAV": ["4th Previous Qtr NAV"],
    "Annualised_Return_Yield": ["Annualised Return/Yield"],
    "Three_Year_Rolling_CAGR": ["3 Year Rolling CAGR"],
    "Highest_NAV_since_inception": ["Highest NAV since inception"]
  },
  "FlatHeaders": [
    "No",
    "Fund_Name",
    "SFIN",
    "Date_of_Launch",
    "Par_Non_Par",
    "Assets_Under_Management",
    "NAV_as_per_LB2",
    "NAV_as_on_above_date",
    "Previous_Qtr_NAV",
    "Second_Previous_Qtr_NAV",
    "Third_Previous_Qtr_NAV",
    "Fourth_Previous_Qtr_NAV",
    "Annualised_Return_Yield",
    "Three_Year_Rolling_CAGR",
    "Highest_NAV_since_inception"
  ],
  "Rows": []
}
